string_generator/__init__.py
string_generator/string_gen.py
random_string_generator-0.0.6.dist-info/LICENSE
random_string_generator-0.0.6.dist-info/METADATA
random_string_generator-0.0.6.dist-info/WHEEL
random_string_generator-0.0.6.dist-info/top_level.txt
random_string_generator-0.0.6.dist-info/RECORD
