Metadata-Version: 2.1
Name: random-string-generator
Version: 0.0.6
Summary: A package to Generate random string
Home-page: https://github.com/pypa/sampleproject
Author: M. Adnan Jakati
Author-email: adnanjackady@gmail.com
Project-URL: Bug Tracker, https://github.com/pypa/sampleproject/issues
Classifier: Programming Language :: Python :: 3
Classifier: License :: OSI Approved :: MIT License
Classifier: Operating System :: OS Independent
Requires-Python: >=3.6
License-File: LICENSE
